MANIFEST.in
README.md
requirements.build.txt
requirements.cpu.txt
requirements.cv.txt
requirements.delft.txt
requirements.dev.txt
requirements.ocr.txt
requirements.txt
setup.py
doc/python_library.md
doc/training.md
sciencebeam_parser/__init__.py
sciencebeam_parser/__main__.py
sciencebeam_parser/cli.py
sciencebeam_parser.egg-info/PKG-INFO
sciencebeam_parser.egg-info/SOURCES.txt
sciencebeam_parser.egg-info/dependency_links.txt
sciencebeam_parser.egg-info/requires.txt
sciencebeam_parser.egg-info/top_level.txt
sciencebeam_parser/app/__init__.py
sciencebeam_parser/app/context.py
sciencebeam_parser/app/parser.py
sciencebeam_parser/config/__init__.py
sciencebeam_parser/config/config.py
sciencebeam_parser/cv_models/__init__.py
sciencebeam_parser/cv_models/cv_model.py
sciencebeam_parser/cv_models/cv_model_factory.py
sciencebeam_parser/cv_models/layout_parser_cv_model.py
sciencebeam_parser/document/__init__.py
sciencebeam_parser/document/layout_document.py
sciencebeam_parser/document/semantic_document.py
sciencebeam_parser/document/tei_document.py
sciencebeam_parser/document/tei/__init__.py
sciencebeam_parser/document/tei/author.py
sciencebeam_parser/document/tei/citation.py
sciencebeam_parser/document/tei/common.py
sciencebeam_parser/document/tei/document.py
sciencebeam_parser/document/tei/equation.py
sciencebeam_parser/document/tei/external_identifiers.py
sciencebeam_parser/document/tei/factories.py
sciencebeam_parser/document/tei/factory.py
sciencebeam_parser/document/tei/figure_table.py
sciencebeam_parser/document/tei/graphic.py
sciencebeam_parser/document/tei/misc.py
sciencebeam_parser/document/tei/page_range.py
sciencebeam_parser/document/tei/references.py
sciencebeam_parser/document/tei/section.py
sciencebeam_parser/external/__init__.py
sciencebeam_parser/external/pdfalto/__init__.py
sciencebeam_parser/external/pdfalto/parser.py
sciencebeam_parser/external/pdfalto/wrapper.py
sciencebeam_parser/external/wapiti/__init__.py
sciencebeam_parser/external/wapiti/wrapper.py
sciencebeam_parser/lookup/__init__.py
sciencebeam_parser/lookup/loader.py
sciencebeam_parser/lookup/xml_lookup.py
sciencebeam_parser/models/__init__.py
sciencebeam_parser/models/data.py
