Metadata-Version: 2.1
Name: sciencebeam-parser
Version: 0.1.7
Summary: ScienceBeam Parser, parse scientific documents.
Home-page: https://github.com/elifesciences/sciencebeam-parser
Author: Daniel Ecer
License: UNKNOWN
Platform: UNKNOWN
Classifier: Programming Language :: Python :: 3
Classifier: License :: OSI Approved :: MIT License
Classifier: Operating System :: OS Independent
